assumptions/__init__.py
assumptions/cli.py
assumptions/log.py
assumptions/log_items.py
assumptions/templates/assumptions_caveats_log.md
assumptions/templates/technical_debt_log.md
assumptions/templates/todo_list.md
assumptions-1.1.0.dist-info/LICENSE
assumptions-1.1.0.dist-info/METADATA
assumptions-1.1.0.dist-info/WHEEL
assumptions-1.1.0.dist-info/entry_points.txt
assumptions-1.1.0.dist-info/top_level.txt
assumptions-1.1.0.dist-info/RECORD
