Metadata-Version: 2.1
Name: assumptions
Version: 1.1.0
Summary: Generating Markdown assumptions logs from code comments.
Home-page: UNKNOWN
Author: David Foster
Author-email: foster.dev999@gmail.com
License: MIT
Platform: UNKNOWN
Classifier: Intended Audience :: Developers
Classifier: License :: OSI Approved :: MIT License
Classifier: Natural Language :: English
Classifier: Operating System :: OS Independent
Classifier: Programming Language :: Python :: 3.6
Classifier: Programming Language :: Python :: 3.7
Classifier: Programming Language :: Python :: 3.8
Classifier: Programming Language :: Python :: 3.9
Classifier: Programming Language :: Python
Classifier: Topic :: Documentation
Classifier: Topic :: Software Development :: Documentation
Classifier: Topic :: Text Processing
Requires-Python: >=3.6
Provides-Extra: dev
Requires-Dist: bump2version ; extra == 'dev'
Requires-Dist: coverage ; extra == 'dev'
Requires-Dist: pytest (<4,>=3.6) ; extra == 'dev'
Requires-Dist: pytest-cov ; extra == 'dev'
Requires-Dist: pytest-regressions ; extra == 'dev'
Provides-Extra: docs
Requires-Dist: assumptions ; extra == 'docs'
Requires-Dist: sphinx ; extra == 'docs'
Requires-Dist: myst-parser ; extra == 'docs'
Requires-Dist: pydata-sphinx-theme ; extra == 'docs'
Requires-Dist: jupyter-sphinx ; extra == 'docs'
Provides-Extra: testing
Requires-Dist: coverage ; extra == 'testing'
Requires-Dist: pytest (<4,>=3.6) ; extra == 'testing'
Requires-Dist: pytest-cov ; extra == 'testing'
Requires-Dist: pytest-regressions ; extra == 'testing'
